gimmebio.assembly-0.9.5-py3.6-nspkg.pth
gimmebio/assembly/__init__.py
gimmebio/assembly/assign_contigs.py
gimmebio/assembly/cli.py
gimmebio/assembly/filter_process.py
gimmebio.assembly-0.9.5.dist-info/METADATA
gimmebio.assembly-0.9.5.dist-info/RECORD
gimmebio.assembly-0.9.5.dist-info/WHEEL
gimmebio.assembly-0.9.5.dist-info/namespace_packages.txt
gimmebio.assembly-0.9.5.dist-info/top_level.txt
